trackio_mcp/__init__.py
trackio_mcp/cli.py
trackio_mcp/monkey_patch.py
trackio_mcp/tools.py
trackio_mcp_fastmcp-0.2.0.dist-info/METADATA
trackio_mcp_fastmcp-0.2.0.dist-info/WHEEL
trackio_mcp_fastmcp-0.2.0.dist-info/entry_points.txt
trackio_mcp_fastmcp-0.2.0.dist-info/licenses/LICENSE
trackio_mcp_fastmcp-0.2.0.dist-info/RECORD
