Metadata-Version: 2.4
Name: trackio-mcp-fastmcp
Version: 0.2.0
Summary: MCP (Model Context Protocol) server support for trackio experiment tracking
Project-URL: Homepage, https://github.com/fastmcp-me/trackio-mcp#readme
Project-URL: Repository, https://github.com/fastmcp-me/trackio-mcp.git
Project-URL: Issues, https://github.com/fastmcp-me/trackio-mcp/issues
Author: Fatih Akyon
License-File: LICENSE
Keywords: AI agents,MCP,Model Context Protocol,experiment tracking,gradio,machine learning,trackio
Classifier: Development Status :: 4 - Beta
Classifier: Intended Audience :: Developers
Classifier: Intended Audience :: Science/Research
Classifier: License :: OSI Approved :: MIT License
Classifier: Operating System :: OS Independent
Classifier: Programming Language :: Python :: 3
Classifier: Programming Language :: Python :: 3.10
Classifier: Programming Language :: Python :: 3.11
Classifier: Programming Language :: Python :: 3.12
Classifier: Topic :: Scientific/Engineering :: Artificial Intelligence
Classifier: Topic :: Scientific/Engineering :: Information Analysis
Classifier: Topic :: Software Development :: Libraries :: Python Modules
Requires-Python: >=3.10
Requires-Dist: gradio[mcp]>=5.35.0
Requires-Dist: requests>=2.25.0
Requires-Dist: trackio==0.2.2
